buzzerboy_saas_tenants/__init__.py
buzzerboy_saas_tenants/core/__init__.py
buzzerboy_saas_tenants/core/adapters.py
buzzerboy_saas_tenants/core/asgi.py
buzzerboy_saas_tenants/core/bedrock.py
buzzerboy_saas_tenants/core/email_service.py
buzzerboy_saas_tenants/core/helpers.py
buzzerboy_saas_tenants/core/jinja2_env.py
buzzerboy_saas_tenants/core/middleware.py
buzzerboy_saas_tenants/core/models.py
buzzerboy_saas_tenants/core/platformConnectors.py
buzzerboy_saas_tenants/core/settings.py
buzzerboy_saas_tenants/core/shortcuts.py
buzzerboy_saas_tenants/core/storages.py
buzzerboy_saas_tenants/core/urls.py
buzzerboy_saas_tenants/core/utils.py
buzzerboy_saas_tenants/core/views.py
buzzerboy_saas_tenants/core/wsgi.py
buzzerboy_saas_tenants/saas_tenants/__init__.py
buzzerboy_saas_tenants/saas_tenants/admin.py
buzzerboy_saas_tenants/saas_tenants/apps.py
buzzerboy_saas_tenants/saas_tenants/utils.py
buzzerboy_saas_tenants/saas_tenants/forms/__init__.py
buzzerboy_saas_tenants/saas_tenants/forms/account_settings.py
buzzerboy_saas_tenants/saas_tenants/forms/accounts.py
buzzerboy_saas_tenants/saas_tenants/forms/authentication.py
buzzerboy_saas_tenants/saas_tenants/forms/invites.py
buzzerboy_saas_tenants/saas_tenants/forms/localization.py
buzzerboy_saas_tenants/saas_tenants/forms/tenant.py
buzzerboy_saas_tenants/saas_tenants/forms/tenant_setting.py
buzzerboy_saas_tenants/saas_tenants/migrations/0001_initial.py
buzzerboy_saas_tenants/saas_tenants/migrations/0002_userprofile_profile_picture_as_path.py
buzzerboy_saas_tenants/saas_tenants/migrations/0003_aichat_complianceframework_chatinteraction_and_more.py
buzzerboy_saas_tenants/saas_tenants/migrations/0004_alter_userprofile_postalcode.py
buzzerboy_saas_tenants/saas_tenants/migrations/0005_remove_usertype_description_remove_usertype_name_and_more.py
buzzerboy_saas_tenants/saas_tenants/migrations/__init__.py
buzzerboy_saas_tenants/saas_tenants/models/__init__.py
buzzerboy_saas_tenants/saas_tenants/models/account_settings.py
buzzerboy_saas_tenants-0.121.3.dist-info/licenses/LICENSE
buzzerboy_saas_tenants-0.121.3.dist-info/METADATA
buzzerboy_saas_tenants-0.121.3.dist-info/WHEEL
buzzerboy_saas_tenants-0.121.3.dist-info/top_level.txt
buzzerboy_saas_tenants-0.121.3.dist-info/RECORD
