Metadata-Version: 2.4
Name: buzzerboy-saas-tenants
Version: 0.121.3
Summary: Buzzerboy SaaS Tenants components that predefines the tenant configuration across for apps
Home-page: https://www.buzzerboy.com/
Author: Buzzerboy Inc
Author-email: Buzzerboy Inc <info@buzzerboy.com>
License: Copyright (c) 2024 Buzzerboy Inc. Canada. All Rights Reserved.
Project-URL: Homepage, https://www.buzzerboy.com/
Project-URL: Issues, https://dev.azure.com/buzzerboyinc/buzzerboy
Classifier: Programming Language :: Python :: 3
Classifier: License :: OSI Approved :: MIT License
Classifier: Operating System :: OS Independent
Requires-Python: >=3.8
License-File: LICENSE
Requires-Dist: django==4.2.9
Requires-Dist: django-allauth==0.60.1
Requires-Dist: PyJWT==2.8.0
Requires-Dist: python-dotenv==1.0.1
Requires-Dist: str2bool==1.1
Requires-Dist: django-quill-editor==0.1.40
Requires-Dist: django-ckeditor==6.7.1
Requires-Dist: django-ckeditor-5==0.2.13
Requires-Dist: jinja2
Requires-Dist: django-htmx==1.19.0
Requires-Dist: django-js-asset==2.2.0
Requires-Dist: celery==5.3.4
Requires-Dist: redis==5.0.1
Requires-Dist: hiredis==2.2.3
Requires-Dist: pillow>=10.0.1
Requires-Dist: django-seed==0.3.1
Requires-Dist: django-celery-results==2.5.1
Requires-Dist: djangorestframework==3.14.0
Requires-Dist: django-api-generator==1.0.17
Requires-Dist: django-debug-toolbar==4.2.0
Requires-Dist: drf-spectacular==0.26.5
Requires-Dist: pyotp
Requires-Dist: django-extensions==3.1.3
Requires-Dist: whitenoise==6.5.0
Requires-Dist: gunicorn==21.2.0
Requires-Dist: cryptography==44.0.0
Requires-Dist: psycopg2-binary
Requires-Dist: python-decouple
Requires-Dist: pandas
Requires-Dist: boto3==1.35.91
Requires-Dist: botocore==1.35.91
Requires-Dist: pyOpenSSL==24.3.0
Requires-Dist: asgiref==3.8.1
Requires-Dist: Faker==28.0.0
Requires-Dist: greenlet==3.0.3
Requires-Dist: Jinja2==3.1.4
Requires-Dist: MarkupSafe==2.1.5
Requires-Dist: psycopg2-binary==2.9.9
Requires-Dist: python-dateutil==2.9.0.post0
Requires-Dist: python-decouple==3.8
Requires-Dist: six==1.16.0
Requires-Dist: sqlparse==0.5.1
Requires-Dist: toposort==1.10
Requires-Dist: python-gettext
Requires-Dist: toml
Requires-Dist: mysqlclient
Requires-Dist: django-ckeditor-5
Requires-Dist: django-storages
Requires-Dist: django-translated-fields
Dynamic: author
Dynamic: home-page
Dynamic: license-file
Dynamic: requires-dist
Dynamic: requires-python
